ztransforms/__init__.py
ztransforms/autoaugment.py
ztransforms/cls_functional.py
ztransforms/cls_transforms.py
ztransforms/functional.py
ztransforms/functional_numpy.py
ztransforms/functional_pil.py
ztransforms/functional_tensor.py
ztransforms/transforms.py
ztransforms/cls/__init__.py
ztransforms/cls/_functional_video.py
ztransforms/cls/_transforms_video.py
ztransforms/cls/autoaugment.py
ztransforms/cls/functional.py
ztransforms/cls/functional_pil.py
ztransforms/cls/functional_tensor.py
ztransforms/cls/transforms.py
ztransforms-0.2.0.dist-info/LICENSE
ztransforms-0.2.0.dist-info/METADATA
ztransforms-0.2.0.dist-info/WHEEL
ztransforms-0.2.0.dist-info/top_level.txt
ztransforms-0.2.0.dist-info/RECORD
