Metadata-Version: 2.1
Name: ztransforms
Version: 0.2.0
Summary: Implementation of torchvision-like based on albumentation
Home-page: https://github.com/ZJCV/ZTransforms
Author: zj
Author-email: wy163zhuj@163.com
License: UNKNOWN
Platform: UNKNOWN
Classifier: Programming Language :: Python :: 3
Classifier: Operating System :: OS Independent
Classifier: License :: OSI Approved :: Apache Software License
Requires-Python: >=3.8
